{
  "TableName": "gramvaani-complaints",
  "KeySchema": [
    {
      "AttributeName": "id",
      "KeyType": "HASH"
    }
  ],
  "AttributeDefinitions": [
    {
      "AttributeName": "id",
      "AttributeType": "S"
    },
    {
      "AttributeName": "timestamp",
      "AttributeType": "S"
    },
    {
      "AttributeName": "village",
      "AttributeType": "S"
    }
  ],
  "GlobalSecondaryIndexes": [
    {
      "IndexName": "timestamp-index",
      "KeySchema": [
        {
          "AttributeName": "timestamp",
          "KeyType": "HASH"
        }
      ],
      "Projection": {
        "ProjectionType": "ALL"
      },
      "ProvisionedThroughput": {
        "ReadCapacityUnits": 5,
        "WriteCapacityUnits": 5
      }
    },
    {
      "IndexName": "village-index",
      "KeySchema": [
        {
          "AttributeName": "village",
          "KeyType": "HASH"
        }
      ],
      "Projection": {
        "ProjectionType": "ALL"
      },
      "ProvisionedThroughput": {
        "ReadCapacityUnits": 5,
        "WriteCapacityUnits": 5
      }
    }
  ],
  "BillingMode": "PROVISIONED",
  "ProvisionedThroughput": {
    "ReadCapacityUnits": 5,
    "WriteCapacityUnits": 5
  }
}
